geosyspy/__init__.py
geosyspy/geosys.py
geosyspy/image_reference.py
geosyspy/services/__init__.py
geosyspy/services/agriquest_service.py
geosyspy/services/analytics_fabric_service.py
geosyspy/services/analytics_processor_service.py
geosyspy/services/gis_service.py
geosyspy/services/map_product_service.py
geosyspy/services/master_data_management_service.py
geosyspy/services/service_constants.py
geosyspy/services/vegetation_time_series_service.py
geosyspy/services/weather_service.py
geosyspy/utils/__init__.py
geosyspy/utils/constants.py
geosyspy/utils/geosys_platform_urls.py
geosyspy/utils/helper.py
geosyspy/utils/http_client.py
geosyspy/utils/jwt_validator.py
geosyspy/utils/logging_config.py
geosyspy/utils/oauth2_client.py
geosyspy-0.2.1.data/data/VERSION.txt
tests/__init__.py
tests/test_helper.py
tests/test_int_geosys.py
tests/test_unit_agriquest_service.py
tests/test_unit_analytics_fabric_service.py
tests/test_unit_analytics_processor_service.py
tests/test_unit_geosys.py
tests/test_unit_gis_service.py
tests/test_unit_http_client.py
tests/test_unit_map_product_service.py
tests/test_unit_master_data_management_service.py
tests/test_unit_oauth2_client.py
tests/test_unit_vegetation_time_series_service.py
tests/test_unit_weather_service.py
geosyspy-0.2.1.dist-info/METADATA
geosyspy-0.2.1.dist-info/WHEEL
geosyspy-0.2.1.dist-info/top_level.txt
geosyspy-0.2.1.dist-info/RECORD
