Metadata-Version: 2.1
Name: geosyspy
Version: 0.2.1
Summary: Easy-to-use python wrapper for Geosys APIs (time series, imagery products)
Author: Geosys
Requires-Dist: requests
Requires-Dist: requests-oauthlib
Requires-Dist: oauthlib
Requires-Dist: scipy
Requires-Dist: pandas
Requires-Dist: shapely
Requires-Dist: rasterio
Requires-Dist: xarray
Requires-Dist: retrying
